MANIFEST.in
README.txt
TODO.txt
VERSION.txt
setup.py
amplikyzer2/__init__.py
amplikyzer2/__main__.py
amplikyzer2/align.py
amplikyzer2/alphabets.py
amplikyzer2/core.py
amplikyzer2/fastq.py
amplikyzer2/flowdna.py
amplikyzer2/graphics.py
amplikyzer2/main.py
amplikyzer2/methylation.py
amplikyzer2/printreads.py
amplikyzer2/sff.py
amplikyzer2/statistics.py
amplikyzer2/utils.py
amplikyzer2.egg-info/PKG-INFO
amplikyzer2.egg-info/SOURCES.txt
amplikyzer2.egg-info/dependency_links.txt
amplikyzer2.egg-info/entry_points.txt
amplikyzer2.egg-info/not-zip-safe
amplikyzer2.egg-info/requires.txt
amplikyzer2.egg-info/top_level.txt
amplikyzer2/analysis/__init__.py
amplikyzer2/analysis/analyze_fastq.py
amplikyzer2/analysis/analyze_sff.py
amplikyzer2/analysis/common.py
amplikyzer2/analysis/mapping.py
amplikyzer2/analysis/scoring/__init__.py
amplikyzer2/analysis/scoring/common.py
amplikyzer2/analysis/scoring/dna.py
amplikyzer2/analysis/scoring/flow.py
amplikyzer2/analysis/scoring/flowdna.py